libpythonpro_zero/__init__.py
libpythonpro_zero/github_api.py
libpythonpro_zero-0.1.dist-info/LICENSE
libpythonpro_zero-0.1.dist-info/METADATA
libpythonpro_zero-0.1.dist-info/WHEEL
libpythonpro_zero-0.1.dist-info/top_level.txt
libpythonpro_zero-0.1.dist-info/RECORD
