Metadata-Version: 2.1
Name: libpythonpro-zero
Version: 0.1
Summary: Modulo para exemplificar construcao de projetos Python no curso pytools
Home-page: https://github.com/FelippeCalcado/libpythonpro_zero
Author: Felippe Calcado
Author-email: felippecalcado@gmail.com
License: GNU AFFERO GENERAL PUBLIC LICENSE
Platform: UNKNOWN
Classifier: Development Status :: 2 - Pre-Alpha
Classifier: Environment :: Console
Classifier: Intended Audience :: Developers
Classifier: License :: OSI Approved :: GNU Affero General Public License v3 or later (AGPLv3+)
Classifier: Operating System :: OS Independent
Classifier: Programming Language :: Python :: 3.6
Classifier: Framework :: Pytest
License-File: LICENSE
Requires-Dist: requests
